ros2_numpy/__init__.py
ros2_numpy/geometry.py
ros2_numpy/image.py
ros2_numpy/occupancy_grid.py
ros2_numpy/point_cloud2.py
ros2_numpy/registry.py
ros2_numpy-0.0.4.dist-info/LICENSE
ros2_numpy-0.0.4.dist-info/METADATA
ros2_numpy-0.0.4.dist-info/WHEEL
ros2_numpy-0.0.4.dist-info/top_level.txt
ros2_numpy-0.0.4.dist-info/RECORD
