Metadata-Version: 2.1
Name: ros2-numpy
Version: 0.0.4
Summary: Convert ROS2 messages to and from numpy arrays
Home-page: https://github.com/nitesh-subedi/ros2_numpy
Author: Tom
Author-email: tom@boxrobotics.ai
Maintainer: Nitesh Subedi
Maintainer-email: 074bme624.nitesh@pcampus.edu.np
License: MIT
Requires-Python: >=3.10
License-File: LICENSE
Requires-Dist: numpy (==1.24.2)
Requires-Dist: transformations
Requires-Dist: pybase64
